podonos/__init__.py
podonos/sdk.py
podonos/common/__init__.py
podonos/common/constant.py
podonos/common/enum.py
podonos/common/exception.py
podonos/common/util.py
podonos/common/validator.py
podonos/core/__init__.py
podonos/core/api.py
podonos/core/base.py
podonos/core/client.py
podonos/core/collection.py
podonos/core/config.py
podonos/core/evaluator.py
podonos/core/file.py
podonos/core/query.py
podonos/core/script.py
podonos/core/stimulus_stats.py
podonos/core/template.py
podonos/core/types.py
podonos/core/upload_manager.py
podonos/entity/__init__.py
podonos/entity/collection.py
podonos/entity/evaluation.py
podonos/entity/script.py
podonos/entity/verification.py
podonos/errors/__init__.py
podonos/errors/error.py
podonos/evaluation/__init__.py
podonos/evaluation/ai_evaluation.py
podonos/evaluation/human_evaluation.py
podonos/service/__init__.py
podonos/service/ai_evaluation_service.py
podonos/service/collection_service.py
podonos/service/evaluation_service.py
podonos/service/script_service.py
podonos/service/template_service.py
podonos-0.31.0.dist-info/licenses/LICENSE
podonos-0.31.0.dist-info/METADATA
podonos-0.31.0.dist-info/WHEEL
podonos-0.31.0.dist-info/top_level.txt
podonos-0.31.0.dist-info/RECORD
