Metadata-Version: 2.4
Name: podonos
Version: 0.31.0
Summary: Managed evaluation for audio & speech
Author-email: David Anderson <david@podonos.com>
License-Expression: MIT
Project-URL: Homepage, https://www.podonos.com
Project-URL: Repository, https://github.com/podonos/podonos-pysdk
Keywords: ai,speech,synthesis
Classifier: Intended Audience :: Science/Research
Classifier: Programming Language :: Python :: 3
Classifier: Programming Language :: Python :: 3.8
Classifier: Programming Language :: Python :: 3.9
Classifier: Programming Language :: Python :: 3.10
Classifier: Programming Language :: Python :: 3.11
Classifier: Programming Language :: Python :: 3.12
Classifier: Topic :: Multimedia :: Sound/Audio :: Analysis
Classifier: Topic :: Multimedia :: Sound/Audio :: Speech
Classifier: Topic :: Scientific/Engineering :: Artificial Intelligence
Requires-Python: >=3.8
License-File: LICENSE
Requires-Dist: glog
Requires-Dist: packaging
Requires-Dist: requests
Requires-Dist: soundfile==0.12.1
Requires-Dist: tqdm
Dynamic: license-file
